src/artem/__init__.py
src/artem/artem.py
src/artem/help.txt
src/artem/lib/nar.py
src/artem/lib/pdb.py
artem_rna-0.0.1.dist-info/METADATA
artem_rna-0.0.1.dist-info/WHEEL
artem_rna-0.0.1.dist-info/licenses/LICENSE
artem_rna-0.0.1.dist-info/RECORD
