Metadata-Version: 2.3
Name: artem-rna
Version: 0.0.1
Summary: Aligning RNA TErtiary Motifs (ARTEM) is a tool for superimposing arbitrary RNA spatial structures
Project-URL: Source, https://github.com/david-bogdan-r/ARTEM.git
Author-email: Davyd R Bohdan <dav.bog.rom@gmail.com>, Janusz M Bujnicki <janusz@iimcb.gov.pl>, Eugene F Baulin <efbaulin@gmail.com>
License-File: LICENSE
Classifier: License :: OSI Approved :: Apache Software License
Classifier: Operating System :: OS Independent
Classifier: Programming Language :: Python :: 3
Classifier: Topic :: Scientific/Engineering :: Bio-Informatics
Requires-Python: >=3.8
Requires-Dist: numpy>=1.22.3
Requires-Dist: pandas>=1.4.1
Requires-Dist: requests>=2.31.0
Requires-Dist: scipy>=1.8.0
